{
  "gitSyncId": "638dd7c62913ba43778b9145_638ee3d19956db2c13d12241",
  "id": "PR Details_InitUtils.storePRFailures",
  "pluginId": "js-plugin",
  "pluginType": "JS",
  "unpublishedAction": {
    "actionConfiguration": {
      "encodeParamsToggle": true,
      "isAsync": true,
      "jsArguments": [],
      "paginationType": "NONE",
      "timeoutInMillisecond": 10000
    },
    "collectionId": "PR Details_InitUtils",
    "confirmBeforeExecute": false,
    "datasource": {
      "isAutoGenerated": false,
      "name": "UNUSED_DATASOURCE",
      "pluginId": "js-plugin"
    },
    "dynamicBindingPathList": [
      {
        "key": "body"
      }
    ],
    "executeOnLoad": false,
    "fullyQualifiedName": "InitUtils.storePRFailures",
    "name": "storePRFailures",
    "pageId": "PR Details",
    "userSetOnLoad": false
  }
}